{"cameraMode":{"drawMode":0,"name":"Shaded","section":"Shading Mode"},"sceneLighting":false,"audioPlay":false,"sceneViewState":{"showFog":true,"showMaterialUpdate":false,"showSkybox":false,"showFlares":true,"showImageEffects":true,"showParticleSystems":true},"in2DMode":false,"pivot":{"x":-2.384185791015625e-7,"y":-2.384185791015625e-7,"z":0.0},"rotation":{"x":0.25289636850357058,"y":0.6324447393417358,"z":-0.23006437718868257,"w":0.6951246857643127},"size":2.6632769107818605,"orthographic":false}